orbitronomy/__init__.py
orbitronomy/highLevel/__init__.py
orbitronomy/highLevel/datasetOrbit.py
orbitronomy/highLevel/orbitCalcs.py
orbitronomy/highLevel/orbit_calculator.py
orbitronomy/highLevel/relativeOrbit.py
orbitronomy/ingredientes/__init__.py
orbitronomy/ingredientes/features.py
orbitronomy-0.3.3.dist-info/METADATA
orbitronomy-0.3.3.dist-info/WHEEL
orbitronomy-0.3.3.dist-info/top_level.txt
orbitronomy-0.3.3.dist-info/RECORD
